Metadata-Version: 2.1
Name: python-unit-prettifier
Version: 1.0.0
Summary: Pretty print various units like digital units, weights, and heights, etc. Easy to implement, but why reinvent the wheel!
Author-email: Aria Bagheri <ariab9342@gmail.com>
License: MIT License
Project-URL: Homepage, https://github.com/AriaBagheri/python_unit_prettifier
Keywords: python,units,formatting,user interface,ui
Classifier: License :: OSI Approved :: MIT License
Classifier: Programming Language :: Python
Classifier: Programming Language :: Python :: 3
Requires-Python: >=3.9
License-File: LICENSE
License-File: AUTHORS.rst
